blm/__init__.py
blm/cli.py
blm/client.py
brainlift/__init__.py
brainlift/serverless/__init__.py
brainlift/serverless/client.py
brainlift-0.2.0.dist-info/licenses/LICENSE
tests/__init__.py
tests/test_cli.py
brainlift-0.2.0.dist-info/METADATA
brainlift-0.2.0.dist-info/WHEEL
brainlift-0.2.0.dist-info/entry_points.txt
brainlift-0.2.0.dist-info/top_level.txt
brainlift-0.2.0.dist-info/RECORD
